MANIFEST.in
README.md
requirements.txt
setup.py
somebod/__init__.py
somebod/dateutils.py
somebod/decorators.py
somebod/humanize.py
somebod/scripting.py
somebod/system.py
somebod.egg-info/PKG-INFO
somebod.egg-info/SOURCES.txt
somebod.egg-info/dependency_links.txt
somebod.egg-info/requires.txt
somebod.egg-info/top_level.txt