Metadata-Version: 1.0
Name: somebod
Version: 0.1.1
Summary: Somebod contrib
Home-page: https://github.com/gtnx/somebod
Author: Guillaume Thomas
Author-email: guillaume.thomas642@gmail.com
License: LICENCE.txt
Platform: UNKNOWN
